tiffx/__init__.py
tiffx/tiffx.py
tiffx-0.1.2.dist-info/METADATA
tiffx-0.1.2.dist-info/WHEEL
tiffx-0.1.2.dist-info/top_level.txt
tiffx-0.1.2.dist-info/RECORD
