Metadata-Version: 2.1
Name: tiffx
Version: 0.1.2
Summary: A package for managing tiff-like whole slide image with annotation using HDF5
Home-page: UNKNOWN
Author: Zhi Huang
Author-email: zhihuang.ai@gmail.com
License: UNKNOWN
Platform: UNKNOWN
Classifier: Development Status :: 3 - Alpha
Classifier: Intended Audience :: Developers
Classifier: License :: OSI Approved :: MIT License
Classifier: Programming Language :: Python :: 3
Classifier: Programming Language :: Python :: 3.6
Classifier: Programming Language :: Python :: 3.7
Classifier: Programming Language :: Python :: 3.8
Classifier: Programming Language :: Python :: 3.9
Classifier: Programming Language :: Python :: 3.10
Classifier: Operating System :: OS Independent
Requires-Python: >=3.6
Requires-Dist: numpy
Requires-Dist: pandas
Requires-Dist: Pillow
Requires-Dist: h5py
Requires-Dist: tablesopenslide-python
